[
	{
		"yearMonth": "202404",
		"imgs": [
			{
				"imgTitle": "",
				"imgName": "IMG_20240425_083610.jpg"
			},{
				"imgTitle": "",
				"imgName": "IMG_20240425_083617.jpg"
			}
		]
	},{
		"yearMonth": "202405",
		"imgs": [
			{
				"imgTitle": "",
				"imgName": "IMG_20240503_172738.jpg"
			},{
				"imgTitle": "",
				"imgName": "IMG_20240504_092301.jpg"
			},{
				"imgTitle": "",
				"imgName": "IMG_20240505_095333.jpg"
			},{
				"imgTitle": "",
				"imgName": "IMG_20240505_095349.jpg"
			},{
				"imgTitle": "",
				"imgName": "IMG_20240505_203042.jpg"
			},{
				"imgTitle": "",
				"imgName": "IMG_20240506_203931.jpg"
			},{
				"imgTitle": "",
				"imgName": "IMG_20240508_202305.jpg"
			},{
				"imgTitle": "",
				"imgName": "IMG_20240508_202336.jpg"
			},{
				"imgTitle": "",
				"imgName": "IMG_20240511_074726.jpg"
			},{
				"imgTitle": "",
				"imgName": "IMG_20240512_073913.jpg"
			},{
				"imgTitle": "",
				"imgName": "IMG_20240512_081737.jpg"
			},{
				"imgTitle": "",
				"imgName": "IMG_20240512_104841.jpg"
			},{
				"imgTitle": "",
				"imgName": "IMG_20240513_052958.jpg"
			},{
				"imgTitle": "",
				"imgName": "IMG_20240514_071811.jpg"
			},{
				"imgTitle": "",
				"imgName": "IMG_20240514_195110.jpg"
			},{
				"imgTitle": "",
				"imgName": "IMG_20240516_064901.jpg"
			},{
				"imgTitle": "",
				"imgName": "IMG_20240516_064906.jpg"
			},{
				"imgTitle": "",
				"imgName": "IMG_20240518_124901.jpg"
			},{
				"imgTitle": "",
				"imgName": "IMG_20240518_145659.jpg"
			},{
				"imgTitle": "",
				"imgName": "IMG_20240518_145703.jpg"
			},{
				"imgTitle": "",
				"imgName": "IMG_20240519_181247.jpg"
			},{
				"imgTitle": "",
				"imgName": "IMG_20240520_195706.jpg"
			},{
				"imgTitle": "",
				"imgName": "IMG_20240520_195720.jpg"
			},{
				"imgTitle": "",
				"imgName": "IMG_20240520_195735.jpg"
			},{
				"imgTitle": "",
				"imgName": "IMG_20240521_052932.jpg"
			},{
				"imgTitle": "",
				"imgName": "IMG_20240521_184917.jpg"
			},{
				"imgTitle": "",
				"imgName": "IMG_20240522_074117.jpg"
			}
		]
	}
]